supabase_mcp/__init__.py
supabase_mcp/exceptions.py
supabase_mcp/logger.py
supabase_mcp/main.py
supabase_mcp/settings.py
supabase_mcp/clients/api_client.py
supabase_mcp/clients/base_http_client.py
supabase_mcp/clients/management_client.py
supabase_mcp/clients/sdk_client.py
supabase_mcp/core/__init__.py
supabase_mcp/core/container.py
supabase_mcp/core/feature_manager.py
supabase_mcp/services/__init__.py
supabase_mcp/services/api/__init__.py
supabase_mcp/services/api/api_manager.py
supabase_mcp/services/api/spec_manager.py
supabase_mcp/services/api/specs/api_spec.json
supabase_mcp/services/database/__init__.py
supabase_mcp/services/database/migration_manager.py
supabase_mcp/services/database/postgres_client.py
supabase_mcp/services/database/query_manager.py
supabase_mcp/services/database/sql/loader.py
supabase_mcp/services/database/sql/models.py
supabase_mcp/services/database/sql/validator.py
supabase_mcp/services/database/sql/queries/create_migration.sql
supabase_mcp/services/database/sql/queries/get_migrations.sql
supabase_mcp/services/database/sql/queries/get_schemas.sql
supabase_mcp/services/database/sql/queries/get_table_schema.sql
supabase_mcp/services/database/sql/queries/get_tables.sql
supabase_mcp/services/database/sql/queries/init_migrations.sql
supabase_mcp/services/database/sql/queries/logs/auth_logs.sql
supabase_mcp/services/database/sql/queries/logs/cron_logs.sql
supabase_mcp/services/database/sql/queries/logs/edge_logs.sql
supabase_mcp/services/database/sql/queries/logs/function_edge_logs.sql
supabase_mcp/services/database/sql/queries/logs/pgbouncer_logs.sql
supabase_mcp/services/database/sql/queries/logs/postgres_logs.sql
supabase_mcp/services/database/sql/queries/logs/postgrest_logs.sql
supabase_mcp/services/database/sql/queries/logs/realtime_logs.sql
supabase_mcp/services/database/sql/queries/logs/storage_logs.sql
supabase_mcp/services/database/sql/queries/logs/supavisor_logs.sql
supabase_mcp/services/logs/__init__.py
iflow_mcp_supabase_mcp_server-0.4.2.dist-info/METADATA
iflow_mcp_supabase_mcp_server-0.4.2.dist-info/WHEEL
iflow_mcp_supabase_mcp_server-0.4.2.dist-info/entry_points.txt
iflow_mcp_supabase_mcp_server-0.4.2.dist-info/licenses/LICENSE
iflow_mcp_supabase_mcp_server-0.4.2.dist-info/RECORD
