Metadata-Version: 2.4
Name: iflow-mcp_supabase-mcp-server
Version: 0.4.2
Summary: Community Supabase MCP server that enables Cursor and Windsurf to end-to-end manage your Supabase project, execute SQL queries, and more.
Project-URL: Homepage, https://github.com/alexander-zuev/supabase-mcp-server
Project-URL: Repository, https://github.com/alexander-zuev/supabase-mcp-server.git
Project-URL: Changelog, https://github.com/alexander-zuev/supabase-mcp-server/blob/main/CHANGELOG.MD
Project-URL: Documentation, https://github.com/alexander-zuev/supabase-mcp-server#readme
Author-email: Alexander Zuev <azuev@outlook.com>
License-Expression: Apache-2.0
License-File: LICENSE
Keywords: claude,cline,cursor,mcp,model-context-protocol,supabase,windsurf
Classifier: Development Status :: 4 - Beta
Classifier: Intended Audience :: Developers
Classifier: License :: OSI Approved :: Apache Software License
Classifier: Programming Language :: Python :: 3.12
Classifier: Topic :: Database :: Database Engines/Servers
Classifier: Topic :: Software Development :: Libraries :: Python Modules
Requires-Python: >=3.12
Requires-Dist: asyncpg>=0.30.0
Requires-Dist: logfire[system-metrics]>=3.12.0
Requires-Dist: mcp[cli]>=1.4.1
Requires-Dist: pglast>=7.3
Requires-Dist: pyyaml>=6.0.2
Requires-Dist: supabase>=2.13.0
Requires-Dist: tenacity>=9.0.0
